{"variants": [{"style": "straight_news", "headline": "Mathaf Opens 'Resolutions' Exhibition Marking 15 Years of Museum", "rationale": "Entity-first headline with classic Qatar Living structure, focusing on the museum and its milestone.", "word_count": 9, "char_count": 64, "entity_first_score": 100}, {"style": "context_led", "headline": "Qatar Museums Announces 'Resolutions' Exhibition at Mathaf for 15th Anniversary", "rationale": "Leads with the organization (Qatar Museums) and provides institutional context for the exhibition.", "word_count": 10, "char_count": 79, "entity_first_score": 100}, {"style": "number_or_date", "headline": "15 Years of Mathaf Celebrated With 'Resolutions' Exhibition Opening June 10", "rationale": "Leads with the anniversary number and concrete date, making it operational and factual.", "word_count": 11, "char_count": 75, "entity_first_score": 100}], "provider": "static", "model": "offline"}